docs_src/conf.py
docs_src/favicon.png
docs_src/themes/psychopy_plugin/static/Nottingham Supported.png
docs_src/themes/psychopy_plugin/static/Psychopy Plugin Header Large.png
docs_src/themes/psychopy_plugin/static/Psychopy Plugin Header Small.png
psychopy_cedrus/__init__.py
psychopy_cedrus/base.py
psychopy_cedrus/cedrus.py
psychopy_cedrus/lumina.py
psychopy_cedrus/rb.py
psychopy_cedrus/riponda.py
psychopy_cedrus/stimtracker.py
psychopy_cedrus/components/__init__.py
psychopy_cedrus/components/lumina.py
psychopy_cedrus/components/rb.py
psychopy_cedrus/components/riponda.py
psychopy_cedrus/components/stimtracker.py
psychopy_cedrus/components/util.py
psychopy_cedrus/components/cedrusBox/__init__.py
psychopy_cedrus/components/cedrusBox/classic/cedrus@2x.png
psychopy_cedrus/components/cedrusBox/classic/cedrusBox.png
psychopy_cedrus/components/cedrusBox/dark/cedrusBox.png
psychopy_cedrus/components/cedrusBox/dark/cedrusBox@2x.png
psychopy_cedrus/components/cedrusBox/light/cedrusBox.png
psychopy_cedrus/components/cedrusBox/light/cedrusBox@2x.png
psychopy_cedrus-0.1.3.dist-info/licenses/LICENSE
tests/__init__.py
tests/test_builder/__init__.py
tests/test_builder/test_ExampleComponent.py
tests/test_coder/__init__.py
psychopy_cedrus-0.1.3.dist-info/METADATA
psychopy_cedrus-0.1.3.dist-info/WHEEL
psychopy_cedrus-0.1.3.dist-info/entry_points.txt
psychopy_cedrus-0.1.3.dist-info/top_level.txt
psychopy_cedrus-0.1.3.dist-info/RECORD
